tinman/__init__.py
tinman/tinman.py
tinman/agents/__init__.py
tinman/agents/base.py
tinman/agents/experiment_architect.py
tinman/agents/experiment_executor.py
tinman/agents/failure_discovery.py
tinman/agents/hypothesis_engine.py
tinman/agents/intervention_engine.py
tinman/agents/simulation_engine.py
tinman/cli/__init__.py
tinman/cli/main.py
tinman/config/__init__.py
tinman/config/modes.py
tinman/config/settings.py
tinman/core/__init__.py
tinman/core/approval_gate.py
tinman/core/approval_handler.py
tinman/core/control_plane.py
tinman/core/cost_tracker.py
tinman/core/event_bus.py
tinman/core/exceptions.py
tinman/core/metrics.py
tinman/core/risk_evaluator.py
tinman/core/risk_policy.py
tinman/core/tools.py
tinman/db/__init__.py
tinman/db/audit.py
tinman/db/connection.py
tinman/db/models.py
tinman/demo/__init__.py
tinman/demo/__main__.py
tinman/demo/env_check.py
tinman/demo/fal_demo.py
tinman/demo/github_demo.py
tinman/demo/huggingface_demo.py
tinman/demo/replicate_demo.py
tinman/demo/runner.py
tinman/ingest/__init__.py
tinman/ingest/base.py
tinman/ingest/datadog.py
tinman/ingest/json_adapter.py
tinman/ingest/otlp.py
tinman/ingest/registry.py
tinman/ingest/xray.py
tinman/integrations/__init__.py
tinman/integrations/anthropic_client.py
tinman/integrations/crewai.py
tinman/integrations/fastapi.py
tinman/integrations/google_client.py
tinman/integrations/groq_client.py
tinman/integrations/langchain.py
tinman/integrations/model_client.py
tinman/integrations/ollama_client.py
tinman/integrations/openai_client.py
tinman/integrations/openrouter_client.py
tinman/integrations/pipeline_adapter.py
tinman/integrations/rate_limiter.py
tinman/integrations/together_client.py
tinman/integrations/token_counter.py
tinman/integrations/gateway_plugin/__init__.py
tinman/integrations/gateway_plugin/alerter.py
tinman/integrations/gateway_plugin/base.py
tinman/integrations/gateway_plugin/monitor.py
tinman/memory/__init__.py
tinman/memory/graph.py
tinman/memory/models.py
agenttinman-0.2.1.dist-info/METADATA
agenttinman-0.2.1.dist-info/WHEEL
agenttinman-0.2.1.dist-info/entry_points.txt
agenttinman-0.2.1.dist-info/licenses/LICENSE
agenttinman-0.2.1.dist-info/RECORD
