Metadata-Version: 2.4
Name: AgentTinman
Version: 0.2.1
Summary: Forward-Deployed Research Agent for AI system failure discovery
Project-URL: Homepage, https://github.com/oliveskin/agent_tinman
Project-URL: Documentation, https://github.com/oliveskin/agent_tinman#readme
Project-URL: Repository, https://github.com/oliveskin/agent_tinman
Project-URL: Issues, https://github.com/oliveskin/agent_tinman/issues
Author: Tinman Contributors
License-Expression: Apache-2.0
License-File: LICENSE
Keywords: ai,failure-discovery,llm,research,safety,testing
Classifier: Development Status :: 4 - Beta
Classifier: Intended Audience :: Developers
Classifier: Intended Audience :: Science/Research
Classifier: License :: OSI Approved :: Apache Software License
Classifier: Programming Language :: Python :: 3
Classifier: Programming Language :: Python :: 3.10
Classifier: Programming Language :: Python :: 3.11
Classifier: Programming Language :: Python :: 3.12
Classifier: Topic :: Scientific/Engineering :: Artificial Intelligence
Classifier: Topic :: Software Development :: Testing
Requires-Python: >=3.10
Requires-Dist: alembic>=1.13.0
Requires-Dist: click>=8.1.0
Requires-Dist: psycopg2-binary>=2.9.0
Requires-Dist: pydantic>=2.0.0
Requires-Dist: python-dotenv>=1.0.0
Requires-Dist: pyyaml>=6.0
Requires-Dist: sqlalchemy>=2.0.0
Requires-Dist: structlog>=24.0.0
Provides-Extra: all
Requires-Dist: anthropic>=0.20.0; extra == 'all'
Requires-Dist: fastapi>=0.115.10; extra == 'all'
Requires-Dist: google-genai>=0.4.0; extra == 'all'
Requires-Dist: openai>=1.0.0; extra == 'all'
Requires-Dist: prometheus-client>=0.20.0; extra == 'all'
Requires-Dist: starlette<0.47.0,>=0.40.0; extra == 'all'
Requires-Dist: uvicorn>=0.27.0; extra == 'all'
Provides-Extra: anthropic
Requires-Dist: anthropic>=0.20.0; extra == 'anthropic'
Provides-Extra: dev
Requires-Dist: mkdocs-material>=9.5.0; extra == 'dev'
Requires-Dist: mkdocs>=1.5.0; extra == 'dev'
Requires-Dist: mypy>=1.8.0; extra == 'dev'
Requires-Dist: pymdown-extensions>=10.0; extra == 'dev'
Requires-Dist: pytest-asyncio>=0.23.0; extra == 'dev'
Requires-Dist: pytest-cov>=4.1.0; extra == 'dev'
Requires-Dist: pytest>=8.0.0; extra == 'dev'
Requires-Dist: ruff>=0.3.0; extra == 'dev'
Provides-Extra: google
Requires-Dist: google-genai>=0.4.0; extra == 'google'
Provides-Extra: openai
Requires-Dist: openai>=1.0.0; extra == 'openai'
Provides-Extra: pdf
Requires-Dist: weasyprint>=60.0; extra == 'pdf'
Provides-Extra: service
Requires-Dist: fastapi>=0.115.10; extra == 'service'
Requires-Dist: prometheus-client>=0.20.0; extra == 'service'
Requires-Dist: starlette<0.47.0,>=0.40.0; extra == 'service'
Requires-Dist: uvicorn>=0.27.0; extra == 'service'
